CHANGES.txt
LICENSE
MANIFEST.in
README.rst
setup.cfg
setup.py
baidupush/__init__.py
baidupush/baidupush.py
baidupush.egg-info/PKG-INFO
baidupush.egg-info/SOURCES.txt
baidupush.egg-info/dependency_links.txt
baidupush.egg-info/not-zip-safe
baidupush.egg-info/requires.txt
baidupush.egg-info/top_level.txt