Metadata-Version: 1.0
Name: baidupush
Version: 0.1.1
Summary: Python Client for Baidu Push APIs
Home-page: https://github.com/quatanium/python-baidu-push-server
Author: sinchb
Author-email: sinchb128@gmail.com
License: MIT
Keywords: push,baidu,android
Platform: UNKNOWN
